AUTHORS.rst
CONTRIBUTING.rst
LICENSE.md
MANIFEST.in
README.rst
setup.cfg
setup.py
versioneer.py
docs/Makefile
docs/source/conf.py
docs/source/control.rst
docs/source/devices.rst
docs/source/index.rst
docs/source/installation.rst
docs/source/presentations.rst
docs/source/pvNotepad.rst
docs/source/sample_delivery.rst
docs/source/shared_memory.rst
docs/source/generated/jet_tracking.jet_control.JetControl.calibrate.rst
docs/source/generated/jet_tracking.jet_control.JetControl.jet_calculate.rst
docs/source/generated/jet_tracking.jet_control.JetControl.jet_move.rst
docs/source/generated/jet_tracking.jet_control.JetControl.rst
docs/source/generated/jet_tracking.jet_control.JetControl.set_beam.rst
docs/source/generated/jet_tracking.jet_control.calibrate.rst
docs/source/generated/jet_tracking.jet_control.jet_calculate.rst
docs/source/generated/jet_tracking.jet_control.jet_move.rst
docs/source/generated/jet_tracking.jet_control.set_beam.rst
docs/source/generated/jet_tracking.psana.output_cspad_sum.rst
jet_tracking/__init__.py
jet_tracking/_version.py
jet_tracking/cam_utils.py
jet_tracking/devices.py
jet_tracking/devices_load.py
jet_tracking/interactive_tests.py
jet_tracking/jet_control.py
jet_tracking/move_motor.py
jet_tracking/old_plans.py
jet_tracking/test_plans.py
jet_tracking.egg-info/PKG-INFO
jet_tracking.egg-info/SOURCES.txt
jet_tracking.egg-info/dependency_links.txt
jet_tracking.egg-info/entry_points.txt
jet_tracking.egg-info/requires.txt
jet_tracking.egg-info/top_level.txt
jet_tracking/psana/__init__.py
jet_tracking/psana/psana2epics.py
jet_tracking/tests/__init__.py
jet_tracking/tests/conftest.py
jet_tracking/tests/test_cam_utils.py
jet_tracking/tests/test_control.py
jet_tracking/tests/test_plans.py