Metadata-Version: 1.1
Name: jet-tracking
Version: 0.0.0
Summary: CXI liquid jet positioning feedback and tracking
Home-page: https://github.com/pcdshub/jet_tracking
Author: SLAC National Accelerator Laboratory
Author-email: UNKNOWN
License: SLAC Open License
Platform: UNKNOWN
Classifier: Development Status :: 2 - Pre-Alpha
Classifier: Natural Language :: English
Classifier: Programming Language :: Python :: 3
